requestsWS/__init__.py
requestsWS/misc.py
requestsWS/session.py
requestsWS-0.0.17.dist-info/LICENSE
requestsWS-0.0.17.dist-info/METADATA
requestsWS-0.0.17.dist-info/WHEEL
requestsWS-0.0.17.dist-info/top_level.txt
requestsWS-0.0.17.dist-info/RECORD
